{
  "id": 116,
  "type": 3,
  "name": "Hard Impact",
  "units": "g",
  "unitsType": "IMX_NATIVE",
  "dataType": "IMX_FLOAT",
  "defaultValue": 0,
  "mode": "scalar",
  "states": 0,
  "iconUrl": "https://storage.googleapis.com/imatrix-files/58281061-cfd7-4977-a44d-d673f274a2ec.svg",
  "thresholdQualificationTime": null,
  "minAdvisoryEnabled": false,
  "minAdvisory": 0,
  "minWarningEnabled": false,
  "minWarning": 0,
  "minAlarmEnabled": false,
  "minAlarm": 0,
  "maxAdvisoryEnabled": false,
  "maxAdvisory": 0,
  "maxWarningEnabled": false,
  "maxWarning": 0,
  "maxAlarmEnabled": false,
  "maxAlarm": 0,
  "maxGraph": 1,
  "minGraph": 0,
  "calibrationMode": null,
  "calibrateValue1": null,
  "calibrateValue2": null,
  "calibrateValue3": null,
  "calibrationRef1": null,
  "calibrationRef2": null,
  "calibrationRef3": null
}